MANIFEST.in
README.rst
setup.py
kkb/__init__.py
kkb/kkb_sign.py
kkb/process.py
kkb.egg-info/PKG-INFO
kkb.egg-info/SOURCES.txt
kkb.egg-info/dependency_links.txt
kkb.egg-info/top_level.txt
kkb/templates/kkb/command_template.xml
kkb/templates/kkb/template.xml